{
"A*FL/PW*ET": "abcdefghijklmnopqrstuvwxyz",
"AOE/PHOEPBLG": "emoji",
"KAOL/KAOL/KAOL": "cool cool cool",
"KAOL/KAOL/KAOL/KAOL": "cool. Cool, cool, cool.",
"KAOL/KAOL/KAOL/KAOL/TP-PL": "cool. Cool, cool, cool.",
"PAU/SAEU": "pass\u00e9",
"PHA*EUL": "{>}morinted@gmail.com",
"PHO*ERPB": "Morin",
"PHO*RPB": "Morin",
"PHOERPBTD": "{>}morinted",
"PHORTD": "{>}morinted",
"SHO*PB": "Sch\u00f6n",
"STOEUPB/PWAORBD": "Stenoboard",
"STOEUPB/PWAORD": "Stenoboard",
"STOEUPB/SAURS": "Stenosaurus",
"STOEUPB/SOERS": "Stenosaurus",
"STOEUPB/TAOEUP": "stenotype",
"STOEUPB/TK*EUBGT": "Stenodict",
"STOEUPB/TKEUBGT": "stenodict",
"STOEUPB/TKPWRAF": "stenograph",
"STOEUPB/TKPWRAFBG": "stenographic",
"STOEUPB/TRAEU": "StenoTray",
"TET/REUS": "Tetris",
"TPA*": "ph\u1edf",
"WUZ/WUZ": "{}"
}
